{
  "$schema": "https://developer.microsoft.com/json-schemas/fabric/item/report/definition/visualContainer/2.1.0/schema.json",
  "name": "1f0ce92ac95796c0c699",
  "position": {
    "x": 32.222222222222221,
    "y": 318.88888888888886,
    "z": 2,
    "height": 372.22222222222223,
    "width": 957.77777777777771
  },
  "visual": {
    "visualType": "lineChart",
    "query": {
      "queryState": {
        "Category": {
          "projections": [
            {
              "field": {
                "Column": {
                  "Expression": {
                    "SourceRef": {
                      "Entity": "dCalendario"
                    }
                  },
                  "Property": "Nome do Mes"
                }
              },
              "queryRef": "dCalendario.Nome do Mes",
              "nativeQueryRef": "Nome do Mes",
              "active": true
            }
          ]
        },
        "Y": {
          "projections": [
            {
              "field": {
                "Measure": {
                  "Expression": {
                    "SourceRef": {
                      "Entity": "Medidas"
                    }
                  },
                  "Property": "faturamento"
                }
              },
              "queryRef": "Medidas.faturamento",
              "nativeQueryRef": "faturamento"
            }
          ]
        }
      },
      "sortDefinition": {
        "sort": [
          {
            "field": {
              "Column": {
                "Expression": {
                  "SourceRef": {
                    "Entity": "dCalendario"
                  }
                },
                "Property": "Nome do Mes"
              }
            },
            "direction": "Ascending"
          }
        ]
      }
    },
    "drillFilterOtherVisuals": true
  },
  "filterConfig": {
    "filters": [
      {
        "name": "6ff41de9227602b3a860",
        "field": {
          "Measure": {
            "Expression": {
              "SourceRef": {
                "Entity": "Medidas"
              }
            },
            "Property": "faturamento"
          }
        },
        "type": "Advanced"
      },
      {
        "name": "75ae32d505750a079091",
        "field": {
          "Column": {
            "Expression": {
              "SourceRef": {
                "Entity": "dCalendario"
              }
            },
            "Property": "Nome do Mes"
          }
        },
        "type": "Categorical"
      }
    ]
  }
}